{
  "version": 1,
  "type": "doc",
  "content": [
    {
      "type": "bodiedExtension",
      "attrs": {
        "extensionType": "com.atlassian.confluence.macro.core",
        "extensionKey": "details",
        "parameters": {
          "macroParams": {
            "hidden": {
              "value": "true"
            }
          },
          "macroMetadata": {
            "schemaVersion": {
              "value": "1"
            },
            "title": "Page Properties"
          }
        }
      },
      "content": [
        {
          "type": "table",
          "attrs": {
            "isNumberColumnEnabled": false,
            "layout": "default"
          },
          "content": [
            {
              "type": "tableRow",
              "content": [
                {
                  "type": "tableHeader",
                  "attrs": {
                    "colspan": 1,
                    "background": "#f4f5f7",
                    "rowspan": 1
                  },
                  "content": [
                    {
                      "type": "paragraph",
                      "content": [
                        {
                          "text": "Schema Name",
                          "type": "text",
                          "marks": [
                            {
                              "type": "strong"
                            }
                          ]
                        }
                      ]
                    }
                  ]
                },
                {
                  "type": "tableCell",
                  "attrs": {
                    "colspan": 1,
                    "rowspan": 1
                  },
                  "content": [
                    {
                      "type": "paragraph",
                      "content": [
                        {
                          "text": "Nypa",
                          "type": "text"
                        }
                      ]
                    }
                  ]
                }
              ]
            },
            {
              "type": "tableRow",
              "content": [
                {
                  "type": "tableHeader",
                  "attrs": {
                    "colspan": 1,
                    "background": "#f4f5f7",
                    "rowspan": 1
                  },
                  "content": [
                    {
                      "type": "paragraph",
                      "content": [
                        {
                          "text": "Table Name",
                          "type": "text",
                          "marks": [
                            {
                              "type": "strong"
                            }
                          ]
                        }
                      ]
                    }
                  ]
                },
                {
                  "type": "tableCell",
                  "attrs": {
                    "colspan": 1,
                    "rowspan": 1
                  },
                  "content": [
                    {
                      "type": "paragraph",
                      "content": [
                        {
                          "text": "uvw_CheckNypaMeterBillingPreloadReadingCodeDistribution",
                          "type": "text"
                        }
                      ]
                    }
                  ]
                }
              ]
            },
            {
              "type": "tableRow",
              "content": [
                {
                  "type": "tableHeader",
                  "attrs": {
                    "colspan": 1,
                    "background": "#f4f5f7",
                    "rowspan": 1
                  },
                  "content": [
                    {
                      "type": "paragraph",
                      "content": [
                        {
                          "text": "Complexity Level",
                          "type": "text",
                          "marks": [
                            {
                              "type": "strong"
                            }
                          ]
                        }
                      ]
                    }
                  ]
                },
                {
                  "type": "tableCell",
                  "attrs": {
                    "colspan": 1,
                    "rowspan": 1
                  },
                  "content": [
                    {
                      "type": "paragraph",
                      "content": [
                        {
                          "text": "Medium",
                          "type": "text"
                        }
                      ]
                    }
                  ]
                }
              ]
            },
            {
              "type": "tableRow",
              "content": [
                {
                  "type": "tableHeader",
                  "attrs": {
                    "colspan": 1,
                    "background": "#f4f5f7",
                    "rowspan": 1
                  },
                  "content": [
                    {
                      "type": "paragraph",
                      "content": [
                        {
                          "text": "Column Count",
                          "type": "text",
                          "marks": [
                            {
                              "type": "strong"
                            }
                          ]
                        }
                      ]
                    }
                  ]
                },
                {
                  "type": "tableCell",
                  "attrs": {
                    "colspan": 1,
                    "rowspan": 1
                  },
                  "content": [
                    {
                      "type": "paragraph",
                      "content": [
                        {
                          "text": "20",
                          "type": "text"
                        }
                      ]
                    }
                  ]
                }
              ]
            }
          ]
        }
      ]
    },
    {
      "type": "heading",
      "attrs": {
        "level": 1
      },
      "content": [
        {
          "type": "text",
          "text": "1. Overview"
        }
      ]
    },
    {
      "type": "paragraph",
      "content": [
        {
          "type": "text",
          "text": "The view "
        },
        {
          "type": "text",
          "text": "Nypa.uvw_CheckNypaMeterBillingPreloadReadingCodeDistribution",
          "marks": [
            {
              "type": "code"
            }
          ]
        },
        {
          "type": "text",
          "text": " is designed to provide a structured representation of billing data related to meter readings from the "
        },
        {
          "type": "text",
          "text": "Nypa.UploadNYPAMeterBillingPreload",
          "marks": [
            {
              "type": "code"
            }
          ]
        },
        {
          "type": "text",
          "text": " table. It aggregates and transforms raw data into a more usable format by calculating billed consumption and demand values. The view includes various attributes related to billing periods, account details, and meter readings, which are essential for analyzing and verifying billing information."
        }
      ]
    },
    {
      "type": "heading",
      "attrs": {
        "level": 1
      },
      "content": [
        {
          "type": "text",
          "text": "2. Complexity Level: Medium"
        }
      ]
    },
    {
      "type": "bulletList",
      "content": [
        {
          "type": "listItem",
          "content": [
            {
              "type": "paragraph",
              "content": [
                {
                  "type": "text",
                  "text": "Structure",
                  "marks": [
                    {
                      "type": "strong"
                    }
                  ]
                },
                {
                  "type": "text",
                  "text": ": The view is relatively straightforward, involving a single table ("
                },
                {
                  "type": "text",
                  "text": "Nypa.UploadNYPAMeterBillingPreload",
                  "marks": [
                    {
                      "type": "code"
                    }
                  ]
                },
                {
                  "type": "text",
                  "text": ") and basic SQL operations such as casting and arithmetic operations."
                }
              ]
            }
          ]
        },
        {
          "type": "listItem",
          "content": [
            {
              "type": "paragraph",
              "content": [
                {
                  "type": "text",
                  "text": "Dependencies",
                  "marks": [
                    {
                      "type": "strong"
                    }
                  ]
                },
                {
                  "type": "text",
                  "text": ": It depends on a single user table, which simplifies its dependency structure."
                }
              ]
            }
          ]
        },
        {
          "type": "listItem",
          "content": [
            {
              "type": "paragraph",
              "content": [
                {
                  "type": "text",
                  "text": "SQL Logic",
                  "marks": [
                    {
                      "type": "strong"
                    }
                  ]
                },
                {
                  "type": "text",
                  "text": ": The logic involves simple arithmetic operations and type casting, which are not computationally intensive but require careful handling to ensure data integrity."
                }
              ]
            }
          ]
        }
      ]
    },
    {
      "type": "heading",
      "attrs": {
        "level": 1
      },
      "content": [
        {
          "type": "text",
          "text": "3. Data Model Analysis"
        }
      ]
    },
    {
      "type": "bulletList",
      "content": [
        {
          "type": "listItem",
          "content": [
            {
              "type": "paragraph",
              "content": [
                {
                  "type": "text",
                  "text": "Underlying Table",
                  "marks": [
                    {
                      "type": "strong"
                    }
                  ]
                },
                {
                  "type": "text",
                  "text": ": The view relies on the "
                },
                {
                  "type": "text",
                  "text": "Nypa.UploadNYPAMeterBillingPreload",
                  "marks": [
                    {
                      "type": "code"
                    }
                  ]
                },
                {
                  "type": "text",
                  "text": " table. This table likely contains raw meter billing data, including consumption and demand metrics, which are essential for calculating the billed values."
                }
              ]
            }
          ]
        },
        {
          "type": "listItem",
          "content": [
            {
              "type": "paragraph",
              "content": [
                {
                  "type": "text",
                  "text": "Columns",
                  "marks": [
                    {
                      "type": "strong"
                    }
                  ]
                },
                {
                  "type": "text",
                  "text": ": The view includes a mix of directly selected columns and computed columns. The computed columns ("
                },
                {
                  "type": "text",
                  "text": "BilledConsumption",
                  "marks": [
                    {
                      "type": "code"
                    }
                  ]
                },
                {
                  "type": "text",
                  "text": ", "
                },
                {
                  "type": "text",
                  "text": "BilledCancelConsumption",
                  "marks": [
                    {
                      "type": "code"
                    }
                  ]
                },
                {
                  "type": "text",
                  "text": ", "
                },
                {
                  "type": "text",
                  "text": "BilledDemand",
                  "marks": [
                    {
                      "type": "code"
                    }
                  ]
                },
                {
                  "type": "text",
                  "text": ", "
                },
                {
                  "type": "text",
                  "text": "BilledCancelDemand",
                  "marks": [
                    {
                      "type": "code"
                    }
                  ]
                },
                {
                  "type": "text",
                  "text": ") are derived from existing columns in the underlying table, indicating a transformation layer for raw data."
                }
              ]
            }
          ]
        },
        {
          "type": "listItem",
          "content": [
            {
              "type": "paragraph",
              "content": [
                {
                  "type": "text",
                  "text": "Data Types",
                  "marks": [
                    {
                      "type": "strong"
                    }
                  ]
                },
                {
                  "type": "text",
                  "text": ": The use of "
                },
                {
                  "type": "text",
                  "text": "nvarchar",
                  "marks": [
                    {
                      "type": "code"
                    }
                  ]
                },
                {
                  "type": "text",
                  "text": " for most string fields allows for internationalization and flexibility in data storage, while numeric fields are appropriately cast to handle arithmetic operations."
                }
              ]
            }
          ]
        }
      ]
    },
    {
      "type": "heading",
      "attrs": {
        "level": 1
      },
      "content": [
        {
          "type": "text",
          "text": "4. Business Context and Use Cases"
        }
      ]
    },
    {
      "type": "bulletList",
      "content": [
        {
          "type": "listItem",
          "content": [
            {
              "type": "paragraph",
              "content": [
                {
                  "type": "text",
                  "text": "Purpose",
                  "marks": [
                    {
                      "type": "strong"
                    }
                  ]
                },
                {
                  "type": "text",
                  "text": ": This view is likely used for auditing and verifying the distribution of reading codes and billing calculations. It provides a consolidated view of billing data, which is crucial for billing departments and auditors."
                }
              ]
            }
          ]
        },
        {
          "type": "listItem",
          "content": [
            {
              "type": "paragraph",
              "content": [
                {
                  "type": "text",
                  "text": "Use Cases",
                  "marks": [
                    {
                      "type": "strong"
                    }
                  ]
                },
                {
                  "type": "text",
                  "text": ":"
                }
              ]
            },
            {
              "type": "bulletList",
              "content": [
                {
                  "type": "listItem",
                  "content": [
                    {
                      "type": "paragraph",
                      "content": [
                        {
                          "type": "text",
                          "text": "Generating reports for billing verification and audits."
                        }
                      ]
                    }
                  ]
                },
                {
                  "type": "listItem",
                  "content": [
                    {
                      "type": "paragraph",
                      "content": [
                        {
                          "type": "text",
                          "text": "Analyzing discrepancies in meter readings and billing calculations."
                        }
                      ]
                    }
                  ]
                },
                {
                  "type": "listItem",
                  "content": [
                    {
                      "type": "paragraph",
                      "content": [
                        {
                          "type": "text",
                          "text": "Supporting customer service operations by providing detailed billing information."
                        }
                      ]
                    }
                  ]
                }
              ]
            }
          ]
        }
      ]
    },
    {
      "type": "heading",
      "attrs": {
        "level": 1
      },
      "content": [
        {
          "type": "text",
          "text": "5. Performance Considerations"
        }
      ]
    },
    {
      "type": "bulletList",
      "content": [
        {
          "type": "listItem",
          "content": [
            {
              "type": "paragraph",
              "content": [
                {
                  "type": "text",
                  "text": "Efficiency",
                  "marks": [
                    {
                      "type": "strong"
                    }
                  ]
                },
                {
                  "type": "text",
                  "text": ": The view performs simple arithmetic and casting operations, which are generally efficient. However, performance could be impacted by the size of the "
                },
                {
                  "type": "text",
                  "text": "Nypa.UploadNYPAMeterBillingPreload",
                  "marks": [
                    {
                      "type": "code"
                    }
                  ]
                },
                {
                  "type": "text",
                  "text": " table."
                }
              ]
            }
          ]
        },
        {
          "type": "listItem",
          "content": [
            {
              "type": "paragraph",
              "content": [
                {
                  "type": "text",
                  "text": "Indexing",
                  "marks": [
                    {
                      "type": "strong"
                    }
                  ]
                },
                {
                  "type": "text",
                  "text": ": Ensuring that the underlying table is properly indexed on frequently queried columns (e.g., "
                },
                {
                  "type": "text",
                  "text": "BillingPeriod",
                  "marks": [
                    {
                      "type": "code"
                    }
                  ]
                },
                {
                  "type": "text",
                  "text": ", "
                },
                {
                  "type": "text",
                  "text": "CurrentAccountNumber",
                  "marks": [
                    {
                      "type": "code"
                    }
                  ]
                },
                {
                  "type": "text",
                  "text": ") can enhance performance."
                }
              ]
            }
          ]
        },
        {
          "type": "listItem",
          "content": [
            {
              "type": "paragraph",
              "content": [
                {
                  "type": "text",
                  "text": "Scalability",
                  "marks": [
                    {
                      "type": "strong"
                    }
                  ]
                },
                {
                  "type": "text",
                  "text": ": As the dataset grows, consider partitioning strategies or materialized views to maintain performance."
                }
              ]
            }
          ]
        }
      ]
    },
    {
      "type": "heading",
      "attrs": {
        "level": 1
      },
      "content": [
        {
          "type": "text",
          "text": "6. Security and Access Control"
        }
      ]
    },
    {
      "type": "bulletList",
      "content": [
        {
          "type": "listItem",
          "content": [
            {
              "type": "paragraph",
              "content": [
                {
                  "type": "text",
                  "text": "Access Control",
                  "marks": [
                    {
                      "type": "strong"
                    }
                  ]
                },
                {
                  "type": "text",
                  "text": ": Ensure that only authorized users have access to this view, especially since it contains sensitive billing information."
                }
              ]
            }
          ]
        },
        {
          "type": "listItem",
          "content": [
            {
              "type": "paragraph",
              "content": [
                {
                  "type": "text",
                  "text": "Data Privacy",
                  "marks": [
                    {
                      "type": "strong"
                    }
                  ]
                },
                {
                  "type": "text",
                  "text": ": Implement row-level security if necessary to restrict access to specific accounts or billing periods based on user roles."
                }
              ]
            }
          ]
        },
        {
          "type": "listItem",
          "content": [
            {
              "type": "paragraph",
              "content": [
                {
                  "type": "text",
                  "text": "Auditing",
                  "marks": [
                    {
                      "type": "strong"
                    }
                  ]
                },
                {
                  "type": "text",
                  "text": ": Regularly audit access logs to ensure compliance with data protection regulations."
                }
              ]
            }
          ]
        }
      ]
    },
    {
      "type": "heading",
      "attrs": {
        "level": 1
      },
      "content": [
        {
          "type": "text",
          "text": "7. Potential Issues or Recommendations"
        }
      ]
    },
    {
      "type": "bulletList",
      "content": [
        {
          "type": "listItem",
          "content": [
            {
              "type": "paragraph",
              "content": [
                {
                  "type": "text",
                  "text": "Data Integrity",
                  "marks": [
                    {
                      "type": "strong"
                    }
                  ]
                },
                {
                  "type": "text",
                  "text": ": Ensure that the casting operations do not lead to data loss or inaccuracies, especially when dealing with large numeric values."
                }
              ]
            }
          ]
        },
        {
          "type": "listItem",
          "content": [
            {
              "type": "paragraph",
              "content": [
                {
                  "type": "text",
                  "text": "Error Handling",
                  "marks": [
                    {
                      "type": "strong"
                    }
                  ]
                },
                {
                  "type": "text",
                  "text": ": Consider implementing error handling mechanisms for cases where casting might fail due to unexpected data types or null values."
                }
              ]
            }
          ]
        },
        {
          "type": "listItem",
          "content": [
            {
              "type": "paragraph",
              "content": [
                {
                  "type": "text",
                  "text": "Documentation",
                  "marks": [
                    {
                      "type": "strong"
                    }
                  ]
                },
                {
                  "type": "text",
                  "text": ": Maintain comprehensive documentation for the view, detailing the purpose of each column and the logic behind computed fields."
                }
              ]
            }
          ]
        },
        {
          "type": "listItem",
          "content": [
            {
              "type": "paragraph",
              "content": [
                {
                  "type": "text",
                  "text": "Optimization",
                  "marks": [
                    {
                      "type": "strong"
                    }
                  ]
                },
                {
                  "type": "text",
                  "text": ": Regularly review and optimize the view as business requirements evolve, particularly if new columns are added to the underlying table or if the data volume increases significantly."
                }
              ]
            }
          ]
        }
      ]
    },
    {
      "type": "heading",
      "attrs": {
        "level": 1
      },
      "content": [
        {
          "type": "text",
          "text": "8. Table Columns"
        }
      ]
    },
    {
      "type": "table",
      "attrs": {
        "isNumberColumnEnabled": false,
        "layout": "default"
      },
      "content": [
        {
          "type": "tableRow",
          "content": [
            {
              "type": "tableHeader",
              "attrs": {},
              "content": [
                {
                  "type": "paragraph",
                  "content": [
                    {
                      "type": "text",
                      "text": "Column Name"
                    }
                  ]
                }
              ]
            },
            {
              "type": "tableHeader",
              "attrs": {},
              "content": [
                {
                  "type": "paragraph",
                  "content": [
                    {
                      "type": "text",
                      "text": "Data Type"
                    }
                  ]
                }
              ]
            },
            {
              "type": "tableHeader",
              "attrs": {},
              "content": [
                {
                  "type": "paragraph",
                  "content": [
                    {
                      "type": "text",
                      "text": "Nullable"
                    }
                  ]
                }
              ]
            },
            {
              "type": "tableHeader",
              "attrs": {},
              "content": [
                {
                  "type": "paragraph",
                  "content": [
                    {
                      "type": "text",
                      "text": "Default"
                    }
                  ]
                }
              ]
            },
            {
              "type": "tableHeader",
              "attrs": {},
              "content": [
                {
                  "type": "paragraph",
                  "content": [
                    {
                      "type": "text",
                      "text": "Primary Key"
                    }
                  ]
                }
              ]
            },
            {
              "type": "tableHeader",
              "attrs": {},
              "content": [
                {
                  "type": "paragraph",
                  "content": [
                    {
                      "type": "text",
                      "text": "Foreign Key"
                    }
                  ]
                }
              ]
            },
            {
              "type": "tableHeader",
              "attrs": {},
              "content": [
                {
                  "type": "paragraph",
                  "content": [
                    {
                      "type": "text",
                      "text": "Referenced Table"
                    }
                  ]
                }
              ]
            }
          ]
        },
        {
          "type": "tableRow",
          "content": [
            {
              "type": "tableCell",
              "attrs": {},
              "content": [
                {
                  "type": "paragraph",
                  "content": [
                    {
                      "type": "text",
                      "text": "TableData"
                    }
                  ]
                }
              ]
            },
            {
              "type": "tableCell",
              "attrs": {},
              "content": [
                {
                  "type": "paragraph",
                  "content": [
                    {
                      "type": "text",
                      "text": "varchar"
                    }
                  ]
                }
              ]
            },
            {
              "type": "tableCell",
              "attrs": {},
              "content": [
                {
                  "type": "paragraph",
                  "content": [
                    {
                      "type": "text",
                      "text": "NO"
                    }
                  ]
                }
              ]
            },
            {
              "type": "tableCell",
              "attrs": {},
              "content": [
                {
                  "type": "paragraph",
                  "content": []
                }
              ]
            },
            {
              "type": "tableCell",
              "attrs": {},
              "content": [
                {
                  "type": "paragraph",
                  "content": [
                    {
                      "type": "text",
                      "text": "NO"
                    }
                  ]
                }
              ]
            },
            {
              "type": "tableCell",
              "attrs": {},
              "content": [
                {
                  "type": "paragraph",
                  "content": [
                    {
                      "type": "text",
                      "text": "NO"
                    }
                  ]
                }
              ]
            },
            {
              "type": "tableCell",
              "attrs": {},
              "content": [
                {
                  "type": "paragraph",
                  "content": []
                }
              ]
            }
          ]
        },
        {
          "type": "tableRow",
          "content": [
            {
              "type": "tableCell",
              "attrs": {},
              "content": [
                {
                  "type": "paragraph",
                  "content": [
                    {
                      "type": "text",
                      "text": "BillingPeriod"
                    }
                  ]
                }
              ]
            },
            {
              "type": "tableCell",
              "attrs": {},
              "content": [
                {
                  "type": "paragraph",
                  "content": [
                    {
                      "type": "text",
                      "text": "nvarchar"
                    }
                  ]
                }
              ]
            },
            {
              "type": "tableCell",
              "attrs": {},
              "content": [
                {
                  "type": "paragraph",
                  "content": [
                    {
                      "type": "text",
                      "text": "YES"
                    }
                  ]
                }
              ]
            },
            {
              "type": "tableCell",
              "attrs": {},
              "content": [
                {
                  "type": "paragraph",
                  "content": []
                }
              ]
            },
            {
              "type": "tableCell",
              "attrs": {},
              "content": [
                {
                  "type": "paragraph",
                  "content": [
                    {
                      "type": "text",
                      "text": "NO"
                    }
                  ]
                }
              ]
            },
            {
              "type": "tableCell",
              "attrs": {},
              "content": [
                {
                  "type": "paragraph",
                  "content": [
                    {
                      "type": "text",
                      "text": "NO"
                    }
                  ]
                }
              ]
            },
            {
              "type": "tableCell",
              "attrs": {},
              "content": [
                {
                  "type": "paragraph",
                  "content": []
                }
              ]
            }
          ]
        },
        {
          "type": "tableRow",
          "content": [
            {
              "type": "tableCell",
              "attrs": {},
              "content": [
                {
                  "type": "paragraph",
                  "content": [
                    {
                      "type": "text",
                      "text": "RevisedBillingPeriod"
                    }
                  ]
                }
              ]
            },
            {
              "type": "tableCell",
              "attrs": {},
              "content": [
                {
                  "type": "paragraph",
                  "content": [
                    {
                      "type": "text",
                      "text": "nvarchar"
                    }
                  ]
                }
              ]
            },
            {
              "type": "tableCell",
              "attrs": {},
              "content": [
                {
                  "type": "paragraph",
                  "content": [
                    {
                      "type": "text",
                      "text": "YES"
                    }
                  ]
                }
              ]
            },
            {
              "type": "tableCell",
              "attrs": {},
              "content": [
                {
                  "type": "paragraph",
                  "content": []
                }
              ]
            },
            {
              "type": "tableCell",
              "attrs": {},
              "content": [
                {
                  "type": "paragraph",
                  "content": [
                    {
                      "type": "text",
                      "text": "NO"
                    }
                  ]
                }
              ]
            },
            {
              "type": "tableCell",
              "attrs": {},
              "content": [
                {
                  "type": "paragraph",
                  "content": [
                    {
                      "type": "text",
                      "text": "NO"
                    }
                  ]
                }
              ]
            },
            {
              "type": "tableCell",
              "attrs": {},
              "content": [
                {
                  "type": "paragraph",
                  "content": []
                }
              ]
            }
          ]
        },
        {
          "type": "tableRow",
          "content": [
            {
              "type": "tableCell",
              "attrs": {},
              "content": [
                {
                  "type": "paragraph",
                  "content": [
                    {
                      "type": "text",
                      "text": "CurrentAccountNumber"
                    }
                  ]
                }
              ]
            },
            {
              "type": "tableCell",
              "attrs": {},
              "content": [
                {
                  "type": "paragraph",
                  "content": [
                    {
                      "type": "text",
                      "text": "nvarchar"
                    }
                  ]
                }
              ]
            },
            {
              "type": "tableCell",
              "attrs": {},
              "content": [
                {
                  "type": "paragraph",
                  "content": [
                    {
                      "type": "text",
                      "text": "YES"
                    }
                  ]
                }
              ]
            },
            {
              "type": "tableCell",
              "attrs": {},
              "content": [
                {
                  "type": "paragraph",
                  "content": []
                }
              ]
            },
            {
              "type": "tableCell",
              "attrs": {},
              "content": [
                {
                  "type": "paragraph",
                  "content": [
                    {
                      "type": "text",
                      "text": "NO"
                    }
                  ]
                }
              ]
            },
            {
              "type": "tableCell",
              "attrs": {},
              "content": [
                {
                  "type": "paragraph",
                  "content": [
                    {
                      "type": "text",
                      "text": "NO"
                    }
                  ]
                }
              ]
            },
            {
              "type": "tableCell",
              "attrs": {},
              "content": [
                {
                  "type": "paragraph",
                  "content": []
                }
              ]
            }
          ]
        },
        {
          "type": "tableRow",
          "content": [
            {
              "type": "tableCell",
              "attrs": {},
              "content": [
                {
                  "type": "paragraph",
                  "content": [
                    {
                      "type": "text",
                      "text": "CurrentMeter"
                    }
                  ]
                }
              ]
            },
            {
              "type": "tableCell",
              "attrs": {},
              "content": [
                {
                  "type": "paragraph",
                  "content": [
                    {
                      "type": "text",
                      "text": "nvarchar"
                    }
                  ]
                }
              ]
            },
            {
              "type": "tableCell",
              "attrs": {},
              "content": [
                {
                  "type": "paragraph",
                  "content": [
                    {
                      "type": "text",
                      "text": "YES"
                    }
                  ]
                }
              ]
            },
            {
              "type": "tableCell",
              "attrs": {},
              "content": [
                {
                  "type": "paragraph",
                  "content": []
                }
              ]
            },
            {
              "type": "tableCell",
              "attrs": {},
              "content": [
                {
                  "type": "paragraph",
                  "content": [
                    {
                      "type": "text",
                      "text": "NO"
                    }
                  ]
                }
              ]
            },
            {
              "type": "tableCell",
              "attrs": {},
              "content": [
                {
                  "type": "paragraph",
                  "content": [
                    {
                      "type": "text",
                      "text": "NO"
                    }
                  ]
                }
              ]
            },
            {
              "type": "tableCell",
              "attrs": {},
              "content": [
                {
                  "type": "paragraph",
                  "content": []
                }
              ]
            }
          ]
        },
        {
          "type": "tableRow",
          "content": [
            {
              "type": "tableCell",
              "attrs": {},
              "content": [
                {
                  "type": "paragraph",
                  "content": [
                    {
                      "type": "text",
                      "text": "ProductionAndDeliveryTariff"
                    }
                  ]
                }
              ]
            },
            {
              "type": "tableCell",
              "attrs": {},
              "content": [
                {
                  "type": "paragraph",
                  "content": [
                    {
                      "type": "text",
                      "text": "nvarchar"
                    }
                  ]
                }
              ]
            },
            {
              "type": "tableCell",
              "attrs": {},
              "content": [
                {
                  "type": "paragraph",
                  "content": [
                    {
                      "type": "text",
                      "text": "YES"
                    }
                  ]
                }
              ]
            },
            {
              "type": "tableCell",
              "attrs": {},
              "content": [
                {
                  "type": "paragraph",
                  "content": []
                }
              ]
            },
            {
              "type": "tableCell",
              "attrs": {},
              "content": [
                {
                  "type": "paragraph",
                  "content": [
                    {
                      "type": "text",
                      "text": "NO"
                    }
                  ]
                }
              ]
            },
            {
              "type": "tableCell",
              "attrs": {},
              "content": [
                {
                  "type": "paragraph",
                  "content": [
                    {
                      "type": "text",
                      "text": "NO"
                    }
                  ]
                }
              ]
            },
            {
              "type": "tableCell",
              "attrs": {},
              "content": [
                {
                  "type": "paragraph",
                  "content": []
                }
              ]
            }
          ]
        },
        {
          "type": "tableRow",
          "content": [
            {
              "type": "tableCell",
              "attrs": {},
              "content": [
                {
                  "type": "paragraph",
                  "content": [
                    {
                      "type": "text",
                      "text": "IsTimeOfDayAccount"
                    }
                  ]
                }
              ]
            },
            {
              "type": "tableCell",
              "attrs": {},
              "content": [
                {
                  "type": "paragraph",
                  "content": [
                    {
                      "type": "text",
                      "text": "nvarchar"
                    }
                  ]
                }
              ]
            },
            {
              "type": "tableCell",
              "attrs": {},
              "content": [
                {
                  "type": "paragraph",
                  "content": [
                    {
                      "type": "text",
                      "text": "YES"
                    }
                  ]
                }
              ]
            },
            {
              "type": "tableCell",
              "attrs": {},
              "content": [
                {
                  "type": "paragraph",
                  "content": []
                }
              ]
            },
            {
              "type": "tableCell",
              "attrs": {},
              "content": [
                {
                  "type": "paragraph",
                  "content": [
                    {
                      "type": "text",
                      "text": "NO"
                    }
                  ]
                }
              ]
            },
            {
              "type": "tableCell",
              "attrs": {},
              "content": [
                {
                  "type": "paragraph",
                  "content": [
                    {
                      "type": "text",
                      "text": "NO"
                    }
                  ]
                }
              ]
            },
            {
              "type": "tableCell",
              "attrs": {},
              "content": [
                {
                  "type": "paragraph",
                  "content": []
                }
              ]
            }
          ]
        },
        {
          "type": "tableRow",
          "content": [
            {
              "type": "tableCell",
              "attrs": {},
              "content": [
                {
                  "type": "paragraph",
                  "content": [
                    {
                      "type": "text",
                      "text": "AccountName"
                    }
                  ]
                }
              ]
            },
            {
              "type": "tableCell",
              "attrs": {},
              "content": [
                {
                  "type": "paragraph",
                  "content": [
                    {
                      "type": "text",
                      "text": "nvarchar"
                    }
                  ]
                }
              ]
            },
            {
              "type": "tableCell",
              "attrs": {},
              "content": [
                {
                  "type": "paragraph",
                  "content": [
                    {
                      "type": "text",
                      "text": "YES"
                    }
                  ]
                }
              ]
            },
            {
              "type": "tableCell",
              "attrs": {},
              "content": [
                {
                  "type": "paragraph",
                  "content": []
                }
              ]
            },
            {
              "type": "tableCell",
              "attrs": {},
              "content": [
                {
                  "type": "paragraph",
                  "content": [
                    {
                      "type": "text",
                      "text": "NO"
                    }
                  ]
                }
              ]
            },
            {
              "type": "tableCell",
              "attrs": {},
              "content": [
                {
                  "type": "paragraph",
                  "content": [
                    {
                      "type": "text",
                      "text": "NO"
                    }
                  ]
                }
              ]
            },
            {
              "type": "tableCell",
              "attrs": {},
              "content": [
                {
                  "type": "paragraph",
                  "content": []
                }
              ]
            }
          ]
        },
        {
          "type": "tableRow",
          "content": [
            {
              "type": "tableCell",
              "attrs": {},
              "content": [
                {
                  "type": "paragraph",
                  "content": [
                    {
                      "type": "text",
                      "text": "AccountAddress"
                    }
                  ]
                }
              ]
            },
            {
              "type": "tableCell",
              "attrs": {},
              "content": [
                {
                  "type": "paragraph",
                  "content": [
                    {
                      "type": "text",
                      "text": "nvarchar"
                    }
                  ]
                }
              ]
            },
            {
              "type": "tableCell",
              "attrs": {},
              "content": [
                {
                  "type": "paragraph",
                  "content": [
                    {
                      "type": "text",
                      "text": "YES"
                    }
                  ]
                }
              ]
            },
            {
              "type": "tableCell",
              "attrs": {},
              "content": [
                {
                  "type": "paragraph",
                  "content": []
                }
              ]
            },
            {
              "type": "tableCell",
              "attrs": {},
              "content": [
                {
                  "type": "paragraph",
                  "content": [
                    {
                      "type": "text",
                      "text": "NO"
                    }
                  ]
                }
              ]
            },
            {
              "type": "tableCell",
              "attrs": {},
              "content": [
                {
                  "type": "paragraph",
                  "content": [
                    {
                      "type": "text",
                      "text": "NO"
                    }
                  ]
                }
              ]
            },
            {
              "type": "tableCell",
              "attrs": {},
              "content": [
                {
                  "type": "paragraph",
                  "content": []
                }
              ]
            }
          ]
        },
        {
          "type": "tableRow",
          "content": [
            {
              "type": "tableCell",
              "attrs": {},
              "content": [
                {
                  "type": "paragraph",
                  "content": [
                    {
                      "type": "text",
                      "text": "RecordTypeConsumption"
                    }
                  ]
                }
              ]
            },
            {
              "type": "tableCell",
              "attrs": {},
              "content": [
                {
                  "type": "paragraph",
                  "content": [
                    {
                      "type": "text",
                      "text": "nvarchar"
                    }
                  ]
                }
              ]
            },
            {
              "type": "tableCell",
              "attrs": {},
              "content": [
                {
                  "type": "paragraph",
                  "content": [
                    {
                      "type": "text",
                      "text": "YES"
                    }
                  ]
                }
              ]
            },
            {
              "type": "tableCell",
              "attrs": {},
              "content": [
                {
                  "type": "paragraph",
                  "content": []
                }
              ]
            },
            {
              "type": "tableCell",
              "attrs": {},
              "content": [
                {
                  "type": "paragraph",
                  "content": [
                    {
                      "type": "text",
                      "text": "NO"
                    }
                  ]
                }
              ]
            },
            {
              "type": "tableCell",
              "attrs": {},
              "content": [
                {
                  "type": "paragraph",
                  "content": [
                    {
                      "type": "text",
                      "text": "NO"
                    }
                  ]
                }
              ]
            },
            {
              "type": "tableCell",
              "attrs": {},
              "content": [
                {
                  "type": "paragraph",
                  "content": []
                }
              ]
            }
          ]
        },
        {
          "type": "tableRow",
          "content": [
            {
              "type": "tableCell",
              "attrs": {},
              "content": [
                {
                  "type": "paragraph",
                  "content": [
                    {
                      "type": "text",
                      "text": "RecordTypeDemand"
                    }
                  ]
                }
              ]
            },
            {
              "type": "tableCell",
              "attrs": {},
              "content": [
                {
                  "type": "paragraph",
                  "content": [
                    {
                      "type": "text",
                      "text": "nvarchar"
                    }
                  ]
                }
              ]
            },
            {
              "type": "tableCell",
              "attrs": {},
              "content": [
                {
                  "type": "paragraph",
                  "content": [
                    {
                      "type": "text",
                      "text": "YES"
                    }
                  ]
                }
              ]
            },
            {
              "type": "tableCell",
              "attrs": {},
              "content": [
                {
                  "type": "paragraph",
                  "content": []
                }
              ]
            },
            {
              "type": "tableCell",
              "attrs": {},
              "content": [
                {
                  "type": "paragraph",
                  "content": [
                    {
                      "type": "text",
                      "text": "NO"
                    }
                  ]
                }
              ]
            },
            {
              "type": "tableCell",
              "attrs": {},
              "content": [
                {
                  "type": "paragraph",
                  "content": [
                    {
                      "type": "text",
                      "text": "NO"
                    }
                  ]
                }
              ]
            },
            {
              "type": "tableCell",
              "attrs": {},
              "content": [
                {
                  "type": "paragraph",
                  "content": []
                }
              ]
            }
          ]
        },
        {
          "type": "tableRow",
          "content": [
            {
              "type": "tableCell",
              "attrs": {},
              "content": [
                {
                  "type": "paragraph",
                  "content": [
                    {
                      "type": "text",
                      "text": "ESTOrACT"
                    }
                  ]
                }
              ]
            },
            {
              "type": "tableCell",
              "attrs": {},
              "content": [
                {
                  "type": "paragraph",
                  "content": [
                    {
                      "type": "text",
                      "text": "nvarchar"
                    }
                  ]
                }
              ]
            },
            {
              "type": "tableCell",
              "attrs": {},
              "content": [
                {
                  "type": "paragraph",
                  "content": [
                    {
                      "type": "text",
                      "text": "YES"
                    }
                  ]
                }
              ]
            },
            {
              "type": "tableCell",
              "attrs": {},
              "content": [
                {
                  "type": "paragraph",
                  "content": []
                }
              ]
            },
            {
              "type": "tableCell",
              "attrs": {},
              "content": [
                {
                  "type": "paragraph",
                  "content": [
                    {
                      "type": "text",
                      "text": "NO"
                    }
                  ]
                }
              ]
            },
            {
              "type": "tableCell",
              "attrs": {},
              "content": [
                {
                  "type": "paragraph",
                  "content": [
                    {
                      "type": "text",
                      "text": "NO"
                    }
                  ]
                }
              ]
            },
            {
              "type": "tableCell",
              "attrs": {},
              "content": [
                {
                  "type": "paragraph",
                  "content": []
                }
              ]
            }
          ]
        },
        {
          "type": "tableRow",
          "content": [
            {
              "type": "tableCell",
              "attrs": {},
              "content": [
                {
                  "type": "paragraph",
                  "content": [
                    {
                      "type": "text",
                      "text": "ConsumptionReadingCode"
                    }
                  ]
                }
              ]
            },
            {
              "type": "tableCell",
              "attrs": {},
              "content": [
                {
                  "type": "paragraph",
                  "content": [
                    {
                      "type": "text",
                      "text": "nvarchar"
                    }
                  ]
                }
              ]
            },
            {
              "type": "tableCell",
              "attrs": {},
              "content": [
                {
                  "type": "paragraph",
                  "content": [
                    {
                      "type": "text",
                      "text": "YES"
                    }
                  ]
                }
              ]
            },
            {
              "type": "tableCell",
              "attrs": {},
              "content": [
                {
                  "type": "paragraph",
                  "content": []
                }
              ]
            },
            {
              "type": "tableCell",
              "attrs": {},
              "content": [
                {
                  "type": "paragraph",
                  "content": [
                    {
                      "type": "text",
                      "text": "NO"
                    }
                  ]
                }
              ]
            },
            {
              "type": "tableCell",
              "attrs": {},
              "content": [
                {
                  "type": "paragraph",
                  "content": [
                    {
                      "type": "text",
                      "text": "NO"
                    }
                  ]
                }
              ]
            },
            {
              "type": "tableCell",
              "attrs": {},
              "content": [
                {
                  "type": "paragraph",
                  "content": []
                }
              ]
            }
          ]
        },
        {
          "type": "tableRow",
          "content": [
            {
              "type": "tableCell",
              "attrs": {},
              "content": [
                {
                  "type": "paragraph",
                  "content": [
                    {
                      "type": "text",
                      "text": "DemandReadingCode"
                    }
                  ]
                }
              ]
            },
            {
              "type": "tableCell",
              "attrs": {},
              "content": [
                {
                  "type": "paragraph",
                  "content": [
                    {
                      "type": "text",
                      "text": "nvarchar"
                    }
                  ]
                }
              ]
            },
            {
              "type": "tableCell",
              "attrs": {},
              "content": [
                {
                  "type": "paragraph",
                  "content": [
                    {
                      "type": "text",
                      "text": "YES"
                    }
                  ]
                }
              ]
            },
            {
              "type": "tableCell",
              "attrs": {},
              "content": [
                {
                  "type": "paragraph",
                  "content": []
                }
              ]
            },
            {
              "type": "tableCell",
              "attrs": {},
              "content": [
                {
                  "type": "paragraph",
                  "content": [
                    {
                      "type": "text",
                      "text": "NO"
                    }
                  ]
                }
              ]
            },
            {
              "type": "tableCell",
              "attrs": {},
              "content": [
                {
                  "type": "paragraph",
                  "content": [
                    {
                      "type": "text",
                      "text": "NO"
                    }
                  ]
                }
              ]
            },
            {
              "type": "tableCell",
              "attrs": {},
              "content": [
                {
                  "type": "paragraph",
                  "content": []
                }
              ]
            }
          ]
        },
        {
          "type": "tableRow",
          "content": [
            {
              "type": "tableCell",
              "attrs": {},
              "content": [
                {
                  "type": "paragraph",
                  "content": [
                    {
                      "type": "text",
                      "text": "MeterType"
                    }
                  ]
                }
              ]
            },
            {
              "type": "tableCell",
              "attrs": {},
              "content": [
                {
                  "type": "paragraph",
                  "content": [
                    {
                      "type": "text",
                      "text": "nvarchar"
                    }
                  ]
                }
              ]
            },
            {
              "type": "tableCell",
              "attrs": {},
              "content": [
                {
                  "type": "paragraph",
                  "content": [
                    {
                      "type": "text",
                      "text": "YES"
                    }
                  ]
                }
              ]
            },
            {
              "type": "tableCell",
              "attrs": {},
              "content": [
                {
                  "type": "paragraph",
                  "content": []
                }
              ]
            },
            {
              "type": "tableCell",
              "attrs": {},
              "content": [
                {
                  "type": "paragraph",
                  "content": [
                    {
                      "type": "text",
                      "text": "NO"
                    }
                  ]
                }
              ]
            },
            {
              "type": "tableCell",
              "attrs": {},
              "content": [
                {
                  "type": "paragraph",
                  "content": [
                    {
                      "type": "text",
                      "text": "NO"
                    }
                  ]
                }
              ]
            },
            {
              "type": "tableCell",
              "attrs": {},
              "content": [
                {
                  "type": "paragraph",
                  "content": []
                }
              ]
            }
          ]
        },
        {
          "type": "tableRow",
          "content": [
            {
              "type": "tableCell",
              "attrs": {},
              "content": [
                {
                  "type": "paragraph",
                  "content": [
                    {
                      "type": "text",
                      "text": "ProductionServiceClass"
                    }
                  ]
                }
              ]
            },
            {
              "type": "tableCell",
              "attrs": {},
              "content": [
                {
                  "type": "paragraph",
                  "content": [
                    {
                      "type": "text",
                      "text": "nvarchar"
                    }
                  ]
                }
              ]
            },
            {
              "type": "tableCell",
              "attrs": {},
              "content": [
                {
                  "type": "paragraph",
                  "content": [
                    {
                      "type": "text",
                      "text": "YES"
                    }
                  ]
                }
              ]
            },
            {
              "type": "tableCell",
              "attrs": {},
              "content": [
                {
                  "type": "paragraph",
                  "content": []
                }
              ]
            },
            {
              "type": "tableCell",
              "attrs": {},
              "content": [
                {
                  "type": "paragraph",
                  "content": [
                    {
                      "type": "text",
                      "text": "NO"
                    }
                  ]
                }
              ]
            },
            {
              "type": "tableCell",
              "attrs": {},
              "content": [
                {
                  "type": "paragraph",
                  "content": [
                    {
                      "type": "text",
                      "text": "NO"
                    }
                  ]
                }
              ]
            },
            {
              "type": "tableCell",
              "attrs": {},
              "content": [
                {
                  "type": "paragraph",
                  "content": []
                }
              ]
            }
          ]
        },
        {
          "type": "tableRow",
          "content": [
            {
              "type": "tableCell",
              "attrs": {},
              "content": [
                {
                  "type": "paragraph",
                  "content": [
                    {
                      "type": "text",
                      "text": "BilledConsumption"
                    }
                  ]
                }
              ]
            },
            {
              "type": "tableCell",
              "attrs": {},
              "content": [
                {
                  "type": "paragraph",
                  "content": [
                    {
                      "type": "text",
                      "text": "int"
                    }
                  ]
                }
              ]
            },
            {
              "type": "tableCell",
              "attrs": {},
              "content": [
                {
                  "type": "paragraph",
                  "content": [
                    {
                      "type": "text",
                      "text": "YES"
                    }
                  ]
                }
              ]
            },
            {
              "type": "tableCell",
              "attrs": {},
              "content": [
                {
                  "type": "paragraph",
                  "content": []
                }
              ]
            },
            {
              "type": "tableCell",
              "attrs": {},
              "content": [
                {
                  "type": "paragraph",
                  "content": [
                    {
                      "type": "text",
                      "text": "NO"
                    }
                  ]
                }
              ]
            },
            {
              "type": "tableCell",
              "attrs": {},
              "content": [
                {
                  "type": "paragraph",
                  "content": [
                    {
                      "type": "text",
                      "text": "NO"
                    }
                  ]
                }
              ]
            },
            {
              "type": "tableCell",
              "attrs": {},
              "content": [
                {
                  "type": "paragraph",
                  "content": []
                }
              ]
            }
          ]
        },
        {
          "type": "tableRow",
          "content": [
            {
              "type": "tableCell",
              "attrs": {},
              "content": [
                {
                  "type": "paragraph",
                  "content": [
                    {
                      "type": "text",
                      "text": "BilledCancelConsumption"
                    }
                  ]
                }
              ]
            },
            {
              "type": "tableCell",
              "attrs": {},
              "content": [
                {
                  "type": "paragraph",
                  "content": [
                    {
                      "type": "text",
                      "text": "int"
                    }
                  ]
                }
              ]
            },
            {
              "type": "tableCell",
              "attrs": {},
              "content": [
                {
                  "type": "paragraph",
                  "content": [
                    {
                      "type": "text",
                      "text": "YES"
                    }
                  ]
                }
              ]
            },
            {
              "type": "tableCell",
              "attrs": {},
              "content": [
                {
                  "type": "paragraph",
                  "content": []
                }
              ]
            },
            {
              "type": "tableCell",
              "attrs": {},
              "content": [
                {
                  "type": "paragraph",
                  "content": [
                    {
                      "type": "text",
                      "text": "NO"
                    }
                  ]
                }
              ]
            },
            {
              "type": "tableCell",
              "attrs": {},
              "content": [
                {
                  "type": "paragraph",
                  "content": [
                    {
                      "type": "text",
                      "text": "NO"
                    }
                  ]
                }
              ]
            },
            {
              "type": "tableCell",
              "attrs": {},
              "content": [
                {
                  "type": "paragraph",
                  "content": []
                }
              ]
            }
          ]
        },
        {
          "type": "tableRow",
          "content": [
            {
              "type": "tableCell",
              "attrs": {},
              "content": [
                {
                  "type": "paragraph",
                  "content": [
                    {
                      "type": "text",
                      "text": "BilledDemand"
                    }
                  ]
                }
              ]
            },
            {
              "type": "tableCell",
              "attrs": {},
              "content": [
                {
                  "type": "paragraph",
                  "content": [
                    {
                      "type": "text",
                      "text": "numeric"
                    }
                  ]
                }
              ]
            },
            {
              "type": "tableCell",
              "attrs": {},
              "content": [
                {
                  "type": "paragraph",
                  "content": [
                    {
                      "type": "text",
                      "text": "YES"
                    }
                  ]
                }
              ]
            },
            {
              "type": "tableCell",
              "attrs": {},
              "content": [
                {
                  "type": "paragraph",
                  "content": []
                }
              ]
            },
            {
              "type": "tableCell",
              "attrs": {},
              "content": [
                {
                  "type": "paragraph",
                  "content": [
                    {
                      "type": "text",
                      "text": "NO"
                    }
                  ]
                }
              ]
            },
            {
              "type": "tableCell",
              "attrs": {},
              "content": [
                {
                  "type": "paragraph",
                  "content": [
                    {
                      "type": "text",
                      "text": "NO"
                    }
                  ]
                }
              ]
            },
            {
              "type": "tableCell",
              "attrs": {},
              "content": [
                {
                  "type": "paragraph",
                  "content": []
                }
              ]
            }
          ]
        },
        {
          "type": "tableRow",
          "content": [
            {
              "type": "tableCell",
              "attrs": {},
              "content": [
                {
                  "type": "paragraph",
                  "content": [
                    {
                      "type": "text",
                      "text": "BilledCancelDemand"
                    }
                  ]
                }
              ]
            },
            {
              "type": "tableCell",
              "attrs": {},
              "content": [
                {
                  "type": "paragraph",
                  "content": [
                    {
                      "type": "text",
                      "text": "numeric"
                    }
                  ]
                }
              ]
            },
            {
              "type": "tableCell",
              "attrs": {},
              "content": [
                {
                  "type": "paragraph",
                  "content": [
                    {
                      "type": "text",
                      "text": "YES"
                    }
                  ]
                }
              ]
            },
            {
              "type": "tableCell",
              "attrs": {},
              "content": [
                {
                  "type": "paragraph",
                  "content": []
                }
              ]
            },
            {
              "type": "tableCell",
              "attrs": {},
              "content": [
                {
                  "type": "paragraph",
                  "content": [
                    {
                      "type": "text",
                      "text": "NO"
                    }
                  ]
                }
              ]
            },
            {
              "type": "tableCell",
              "attrs": {},
              "content": [
                {
                  "type": "paragraph",
                  "content": [
                    {
                      "type": "text",
                      "text": "NO"
                    }
                  ]
                }
              ]
            },
            {
              "type": "tableCell",
              "attrs": {},
              "content": [
                {
                  "type": "paragraph",
                  "content": []
                }
              ]
            }
          ]
        }
      ]
    }
  ]
}